ol_openedx_course_sync/__init__.py
ol_openedx_course_sync/admin.py
ol_openedx_course_sync/apps.py
ol_openedx_course_sync/constants.py
ol_openedx_course_sync/models.py
ol_openedx_course_sync/signals.py
ol_openedx_course_sync/tasks.py
ol_openedx_course_sync/utils.py
ol_openedx_course_sync/migrations/0001_initial.py
ol_openedx_course_sync/migrations/__init__.py
ol_openedx_course_sync/settings/__init__.py
ol_openedx_course_sync/settings/common.py
ol_openedx_course_sync/settings/production.py
ol_openedx_course_sync-0.5.2.dist-info/METADATA
ol_openedx_course_sync-0.5.2.dist-info/WHEEL
ol_openedx_course_sync-0.5.2.dist-info/entry_points.txt
ol_openedx_course_sync-0.5.2.dist-info/licenses/LICENCE
ol_openedx_course_sync-0.5.2.dist-info/RECORD
