Metadata-Version: 2.4
Name: ol-openedx-course-sync
Version: 0.5.2
Summary: An Open edX plugin to sync course changes to its reruns.
Author: MIT Office of Digital Learning
License-Expression: BSD-3-Clause
License-File: LICENCE
Requires-Python: >=3.11
Requires-Dist: django>=4.0
Requires-Dist: djangorestframework>=3.14.0
Requires-Dist: edx-django-utils>4.0.0
Requires-Dist: edx-opaque-keys
Requires-Dist: openedx-events
